README.md
setup.py
scripts/songbird
songbird/__init__.py
songbird/citations.bib
songbird/multinomial.py
songbird/parameter_info.py
songbird/util.py
songbird.egg-info/PKG-INFO
songbird.egg-info/SOURCES.txt
songbird.egg-info/dependency_links.txt
songbird.egg-info/entry_points.txt
songbird.egg-info/not-zip-safe
songbird.egg-info/requires.txt
songbird.egg-info/top_level.txt
songbird/q2/__init__.py
songbird/q2/_method.py
songbird/q2/_stats.py
songbird/q2/_summary.py
songbird/q2/_transformer.py
songbird/q2/plugin_setup.py