Metadata-Version: 2.1
Name: songbird
Version: 1.0.2
Summary: Vanilla regression methods for microbiome differential abundance analysis
Home-page: https://github.com/mortonjt/songbird
Author: gneiss development team
Author-email: jamietmorton@gmail.com
Maintainer: gneiss development team
Maintainer-email: jamietmorton@gmail.com
License: BSD-3-Clause
Platform: UNKNOWN
Classifier: Development Status :: 5 - Production/Stable
Classifier: License :: OSI Approved :: BSD License
Classifier: Topic :: Software Development :: Libraries
Classifier: Topic :: Scientific/Engineering
Classifier: Topic :: Scientific/Engineering :: Bio-Informatics
Classifier: Programming Language :: Python :: 3
Classifier: Programming Language :: Python :: 3 :: Only
Classifier: Operating System :: Unix
Classifier: Operating System :: POSIX
Classifier: Operating System :: MacOS :: MacOS X
